poetry_asterisk/__init__.py
poetry_asterisk/__main__.py
poetry_asterisk/poetry_asterisk.py
poetry_asterisk-0.1.1.dist-info/METADATA
poetry_asterisk-0.1.1.dist-info/WHEEL
poetry_asterisk-0.1.1.dist-info/entry_points.txt
poetry_asterisk-0.1.1.dist-info/RECORD
