Metadata-Version: 2.1
Name: poetry-asterisk
Version: 0.1.1
Summary: 
Keywords: poetry,dependencies,versions
Author: chandr-andr (Kiselev Aleksandr)
Author-email: askiselev00@gmail.com
Requires-Python: >=3.8.1,<4.0
Classifier: Intended Audience :: Developers
Classifier: Operating System :: OS Independent
Classifier: Programming Language :: Python
Classifier: Programming Language :: Python :: 3
Classifier: Programming Language :: Python :: 3.9
Classifier: Programming Language :: Python :: 3.10
Classifier: Programming Language :: Python :: 3.11
Classifier: Programming Language :: Python :: 3.12
Classifier: Programming Language :: Python :: 3 :: Only
Classifier: Programming Language :: Python :: 3.8
Classifier: Typing :: Typed
Requires-Dist: pydantic
Requires-Dist: tomlkit
